proj2/suppl/lfsr/lfsr_7b.v


module lfsr_7b(
        input clk,
        input reset,
        input enable,
        output reg [6:0] x
    );


    always @(posedge clk) begin
        if (reset == 1) begin
            x <= 8;
        end
        else if (enable == 1) begin
            x[0] <= x[1];
            x[1] <= x[2];
            x[2] <= x[3];
            x[3] <= x[4];
            x[4] <= x[5];
            x[5] <= x[6];
            x[6] <= x[0] ^ x[1];
        end
        else begin
        
        end
    end

endmodule

proj2/suppl/lfsr/lfsr_7b_tb.v
`timescale 1ns / 1ps
//`timescale 10ns / 1ns delete this one
////////////////////////////////////////////////////////////////////////////////

module lfsr_7b_tb;

	reg clk, enable, reset;
	wire [6:0] lfsr_out;
	
	lfsr_7b lfsr (
			.clk(clk),
			.enable(enable),
			.reset(reset),
			.x(lfsr_out)
			);

	initial 
		begin
		 $dumpfile("lfsr_7b.vcd");
		 $dumpvars(0,lfsr_7b_tb);

		 clk=0;
		 enable=0;
		 reset=0;
		end
   
	always
//		#50 clk = !clk; 
		#10 clk = !clk; 

	initial
	  	begin
		 #200 reset=1; // Test reset
		 #200 reset=0;
		 #100 enable=1;
		 #100 enable=1; 
		 wait (lfsr_out == 8)
		 $finish;	
		end 
   			
endmodule

proj2/suppl/lfsr/lfsr_7b.vcd
$date
	Wed Dec 20 18:35:43 2023
$end
$version
	Icarus Verilog
$end
$timescale
	1ps
$end
$scope module lfsr_7b_tb $end
$var wire 7 ! lfsr_out [6:0] $end
$var reg 1 " clk $end
$var reg 1 # enable $end
$var reg 1 $ reset $end
$scope module lfsr $end
$var wire 1 " clk $end
$var wire 1 # enable $end
$var wire 1 $ reset $end
$var reg 7 % x [6:0] $end
$upscope $end
$upscope $end
$enddefinitions $end
$comment Show the parameter values. $end
$dumpall
$end
#0
$dumpvars
bx %
0$
0#
0"
bx !
$end
#10000
1"
#20000
0"
#30000
1"
#40000
0"
#50000
1"
#60000
0"
#70000
1"
#80000
0"
#90000
1"
#100000
0"
#110000
1"
#120000
0"
#130000
1"
#140000
0"
#150000
1"
#160000
0"
#170000
1"
#180000
0"
#190000
1"
#200000
0"
1$
#210000
b1000 !
b1000 %
1"
#220000
0"
#230000
1"
#240000
0"
#250000
1"
#260000
0"
#270000
1"
#280000
0"
#290000
1"
#300000
0"
#310000
1"
#320000
0"
#330000
1"
#340000
0"
#350000
1"
#360000
0"
#370000
1"
#380000
0"
#390000
1"
#400000
0"
0$
#410000
1"
#420000
0"
#430000
1"
#440000
0"
#450000
1"
#460000
0"
#470000
1"
#480000
0"
#490000
1"
#500000
0"
1#
#510000
b100 !
b100 %
1"
#520000
0"
#530000
b10 !
b10 %
1"
#540000
0"
#550000
b1000001 !
b1000001 %
1"
#560000
0"
#570000
b1100000 !
b1100000 %
1"
#580000
0"
#590000
b110000 !
b110000 %
1"
#600000
0"
#610000
b11000 !
b11000 %
1"
#620000
0"
#630000
b1100 !
b1100 %
1"
#640000
0"
#650000
b110 !
b110 %
1"
#660000
0"
#670000
b1000011 !
b1000011 %
1"
#680000
0"
#690000
b100001 !
b100001 %
1"
#700000
0"
#710000
b1010000 !
b1010000 %
1"
#720000
0"
#730000
b101000 !
b101000 %
1"
#740000
0"
#750000
b10100 !
b10100 %
1"
#760000
0"
#770000
b1010 !
b1010 %
1"
#780000
0"
#790000
b1000101 !
b1000101 %
1"
#800000
0"
#810000
b1100010 !
b1100010 %
1"
#820000
0"
#830000
b1110001 !
b1110001 %
1"
#840000
0"
#850000
b1111000 !
b1111000 %
1"
#860000
0"
#870000
b111100 !
b111100 %
1"
#880000
0"
#890000
b11110 !
b11110 %
1"
#900000
0"
#910000
b1001111 !
b1001111 %
1"
#920000
0"
#930000
b100111 !
b100111 %
1"
#940000
0"
#950000
b10011 !
b10011 %
1"
#960000
0"
#970000
b1001 !
b1001 %
1"
#980000
0"
#990000
b1000100 !
b1000100 %
1"
#1000000
0"
#1010000
b100010 !
b100010 %
1"
#1020000
0"
#1030000
b1010001 !
b1010001 %
1"
#1040000
0"
#1050000
b1101000 !
b1101000 %
1"
#1060000
0"
#1070000
b110100 !
b110100 %
1"
#1080000
0"
#1090000
b11010 !
b11010 %
1"
#1100000
0"
#1110000
b1001101 !
b1001101 %
1"
#1120000
0"
#1130000
b1100110 !
b1100110 %
1"
#1140000
0"
#1150000
b1110011 !
b1110011 %
1"
#1160000
0"
#1170000
b111001 !
b111001 %
1"
#1180000
0"
#1190000
b1011100 !
b1011100 %
1"
#1200000
0"
#1210000
b101110 !
b101110 %
1"
#1220000
0"
#1230000
b1010111 !
b1010111 %
1"
#1240000
0"
#1250000
b101011 !
b101011 %
1"
#1260000
0"
#1270000
b10101 !
b10101 %
1"
#1280000
0"
#1290000
b1001010 !
b1001010 %
1"
#1300000
0"
#1310000
b1100101 !
b1100101 %
1"
#1320000
0"
#1330000
b1110010 !
b1110010 %
1"
#1340000
0"
#1350000
b1111001 !
b1111001 %
1"
#1360000
0"
#1370000
b1111100 !
b1111100 %
1"
#1380000
0"
#1390000
b111110 !
b111110 %
1"
#1400000
0"
#1410000
b1011111 !
b1011111 %
1"
#1420000
0"
#1430000
b101111 !
b101111 %
1"
#1440000
0"
#1450000
b10111 !
b10111 %
1"
#1460000
0"
#1470000
b1011 !
b1011 %
1"
#1480000
0"
#1490000
b101 !
b101 %
1"
#1500000
0"
#1510000
b1000010 !
b1000010 %
1"
#1520000
0"
#1530000
b1100001 !
b1100001 %
1"
#1540000
0"
#1550000
b1110000 !
b1110000 %
1"
#1560000
0"
#1570000
b111000 !
b111000 %
1"
#1580000
0"
#1590000
b11100 !
b11100 %
1"
#1600000
0"
#1610000
b1110 !
b1110 %
1"
#1620000
0"
#1630000
b1000111 !
b1000111 %
1"
#1640000
0"
#1650000
b100011 !
b100011 %
1"
#1660000
0"
#1670000
b10001 !
b10001 %
1"
#1680000
0"
#1690000
b1001000 !
b1001000 %
1"
#1700000
0"
#1710000
b100100 !
b100100 %
1"
#1720000
0"
#1730000
b10010 !
b10010 %
1"
#1740000
0"
#1750000
b1001001 !
b1001001 %
1"
#1760000
0"
#1770000
b1100100 !
b1100100 %
1"
#1780000
0"
#1790000
b110010 !
b110010 %
1"
#1800000
0"
#1810000
b1011001 !
b1011001 %
1"
#1820000
0"
#1830000
b1101100 !
b1101100 %
1"
#1840000
0"
#1850000
b110110 !
b110110 %
1"
#1860000
0"
#1870000
b1011011 !
b1011011 %
1"
#1880000
0"
#1890000
b101101 !
b101101 %
1"
#1900000
0"
#1910000
b1010110 !
b1010110 %
1"
#1920000
0"
#1930000
b1101011 !
b1101011 %
1"
#1940000
0"
#1950000
b110101 !
b110101 %
1"
#1960000
0"
#1970000
b1011010 !
b1011010 %
1"
#1980000
0"
#1990000
b1101101 !
b1101101 %
1"
#2000000
0"
#2010000
b1110110 !
b1110110 %
1"
#2020000
0"
#2030000
b1111011 !
b1111011 %
1"
#2040000
0"
#2050000
b111101 !
b111101 %
1"
#2060000
0"
#2070000
b1011110 !
b1011110 %
1"
#2080000
0"
#2090000
b1101111 !
b1101111 %
1"
#2100000
0"
#2110000
b110111 !
b110111 %
1"
#2120000
0"
#2130000
b11011 !
b11011 %
1"
#2140000
0"
#2150000
b1101 !
b1101 %
1"
#2160000
0"
#2170000
b1000110 !
b1000110 %
1"
#2180000
0"
#2190000
b1100011 !
b1100011 %
1"
#2200000
0"
#2210000
b110001 !
b110001 %
1"
#2220000
0"
#2230000
b1011000 !
b1011000 %
1"
#2240000
0"
#2250000
b101100 !
b101100 %
1"
#2260000
0"
#2270000
b10110 !
b10110 %
1"
#2280000
0"
#2290000
b1001011 !
b1001011 %
1"
#2300000
0"
#2310000
b100101 !
b100101 %
1"
#2320000
0"
#2330000
b1010010 !
b1010010 %
1"
#2340000
0"
#2350000
b1101001 !
b1101001 %
1"
#2360000
0"
#2370000
b1110100 !
b1110100 %
1"
#2380000
0"
#2390000
b111010 !
b111010 %
1"
#2400000
0"
#2410000
b1011101 !
b1011101 %
1"
#2420000
0"
#2430000
b1101110 !
b1101110 %
1"
#2440000
0"
#2450000
b1110111 !
b1110111 %
1"
#2460000
0"
#2470000
b111011 !
b111011 %
1"
#2480000
0"
#2490000
b11101 !
b11101 %
1"
#2500000
0"
#2510000
b1001110 !
b1001110 %
1"
#2520000
0"
#2530000
b1100111 !
b1100111 %
1"
#2540000
0"
#2550000
b110011 !
b110011 %
1"
#2560000
0"
#2570000
b11001 !
b11001 %
1"
#2580000
0"
#2590000
b1001100 !
b1001100 %
1"
#2600000
0"
#2610000
b100110 !
b100110 %
1"
#2620000
0"
#2630000
b1010011 !
b1010011 %
1"
#2640000
0"
#2650000
b101001 !
b101001 %
1"
#2660000
0"
#2670000
b1010100 !
b1010100 %
1"
#2680000
0"
#2690000
b101010 !
b101010 %
1"
#2700000
0"
#2710000
b1010101 !
b1010101 %
1"
#2720000
0"
#2730000
b1101010 !
b1101010 %
1"
#2740000
0"
#2750000
b1110101 !
b1110101 %
1"
#2760000
0"
#2770000
b1111010 !
b1111010 %
1"
#2780000
0"
#2790000
b1111101 !
b1111101 %
1"
#2800000
0"
#2810000
b1111110 !
b1111110 %
1"
#2820000
0"
#2830000
b1111111 !
b1111111 %
1"
#2840000
0"
#2850000
b111111 !
b111111 %
1"
#2860000
0"
#2870000
b11111 !
b11111 %
1"
#2880000
0"
#2890000
b1111 !
b1111 %
1"
#2900000
0"
#2910000
b111 !
b111 %
1"
#2920000
0"
#2930000
b11 !
b11 %
1"
#2940000
0"
#2950000
b1 !
b1 %
1"
#2960000
0"
#2970000
b1000000 !
b1000000 %
1"
#2980000
0"
#2990000
b100000 !
b100000 %
1"
#3000000
0"
#3010000
b10000 !
b10000 %
1"
#3020000
0"
#3030000
b1000 !
b1000 %
1"
