proj1/params.v
`define N_MAX 8
`define M_MAX 9

proj1/counter_4b.v
`timescale 100ps / 1ps 

module counter_4b(input clk, input reset, input enable, output reg [3:0] count);
    
    always @(posedge clk or posedge reset) begin
        if (reset == 1)
            count <= 4'd0;
        else if (enable == 1)
            count <= count + 4'd1;
    end

endmodule

proj1/controller.v
`timescale 100ps / 1ps 

////////////////////////////////////////////////////////////////////////////////// 
//
// Company: Instituto Superior Técnico de Lisboa 
// Module Name: pulseproj
// Description: pulse generator
// 
////////////////////////////////////////////////////////////////////////////////// 
// 0.1 us clock
`include "params.v" 

module controller(
    input clk,
    input start,
    input reset,
    output reg out,
    output reg bist_end,
    output reg running);

    // State Flip-flops
    reg [2:0] state, n_state;
    reg p_start;
    
    // State coding
    localparam [2:0] IDLE = 0, RUN_H = 1, RUN_L = 2, COMPLETED = 3;

    // M and N 
    localparam [3:0] N_MAX = 8;
    localparam [3:0] M_MAX = 9;

    // Regs
    reg pos_start;
    wire [3:0] n, m;

    // wires
    reg n_en, n_rst;
    reg m_en, m_rst;




    always @(posedge clk) begin

        if (reset == 1)
            state <= IDLE;
        else
            state <= n_state;

    end

    // Detects L to H transition on START input
    always @(posedge clk) begin
        if (p_start == 0 && start == 1)
            pos_start <= 1;
        else
            pos_start <= 0;

        p_start <= start;
    end

    always @(*) begin
    
        case (state)
        IDLE: begin
            // Outputs
            out = 0;
            bist_end = 0;
            running = 0;
            // M Counter
            m_en = 0;
            m_rst = 1;
            // N Counter
            n_en = 0;
            n_rst = 1;
            
            if (pos_start == 1) begin
                n_state = RUN_H; 
            end
            else
                n_state = state;
        end

        RUN_H: begin
            // Outputs
            out = 1;
            running = 1;
            bist_end = 0;
            // N Counter
            n_en = 1;
            n_rst = 0;
            // M Counter
            m_en = 0;
            m_rst = 0;

            // Defining the next state
            if (n == `N_MAX-1 && m == `M_MAX) begin
                n_state = COMPLETED;
            end
            else if (n == `N_MAX-1) begin
                n_state = RUN_L;
            end
            else
                n_state = state;
        end

        RUN_L: begin
            // Outputs
            out = 0;
            running = 1;
            bist_end = 0;

            // N Counter
            n_en = 0;
            n_rst = 1;
            // M Counter
            m_en = 1;
            m_rst = 0; 

            // Defining the next state
            n_state = RUN_H;
        end
        
        COMPLETED: begin
            // Outputs
            out = 0;
            running = 0;
            bist_end = 1;

            // M Counter
            m_rst = 1;
            m_en = 0;
            // N Counter
            n_rst = 1;
            n_en = 0;

            if (pos_start == 1) begin
                n_state = RUN_H;
            end
            else begin
                n_state = state;
            end
        end

        default: begin
            // Outputs
            out = 0;
            bist_end = 0;
            running = 0;
            // M Counter
            m_en = 0;
            m_rst = 1;
            // N Counter
            n_en = 0;
            n_rst = 1;

            n_state = IDLE;
        end
        endcase
    end

    // Counters
    counter_4b n_counter (
        .clk(clk),
        .reset(n_rst),
        .enable(n_en),
        .count(n)
    );
    counter_4b m_counter (
        .clk(clk),
        .reset(m_rst),
        .enable(m_en),
        .count(m)
    );

endmodule

proj1/controller_tb.v
`timescale 1ns / 1ps
//`timescale 10ns / 1ns delete this one
////////////////////////////////////////////////////////////////////////////////

module controller_tb;

	reg clk, start, reset;
	wire out, bist_end, running;
	
	controller controller (
			.clk(clk),
			.start(start),
			.reset(reset),
			.out(out),
			.bist_end(bist_end),
			.running(running)
			);

	initial 
		begin
		 $dumpfile("controller_tb.vcd");
		 $dumpvars(0,controller_tb);

		 clk=0;
		 start=0;
		 reset=0;
		end
   
	always
//		#50 clk = !clk; 
		#10 clk = !clk; 

	initial
	  	begin
		 #200 reset=1; // Test reset
		 #200 reset=0;
		 #100 start=1; // test start
		 #50  start=0;
		 #2000 start = 0; // end of simple operation
		 #100 start = 1;
		 #50 start = 0;
		 #2000 reset = 1;
		 #50 start = 1;
		 #50 start = 0;
		 #500 reset = 0;
		 #2000 start = 1;
		 #50 start = 0;
		 #1000 start = 1;
		 #1000 start = 0;
		 #50 start = 1;
		 #500 reset = 1;
		 #50 reset = 0;
		 #2000 $finish;	
		end 
   			
endmodule

proj1/controller_tb.vcd
$date
	Mon Nov 27 12:09:46 2023
$end
$version
	Icarus Verilog
$end
$timescale
	1ps
$end
$scope module controller_tb $end
$var wire 1 ! running $end
$var wire 1 " out $end
$var wire 1 # bist_end $end
$var reg 1 $ clk $end
$var reg 1 % reset $end
$var reg 1 & start $end
$scope module controller $end
$var wire 1 $ clk $end
$var wire 1 % reset $end
$var wire 1 & start $end
$var wire 4 ' n [3:0] $end
$var wire 4 ( m [3:0] $end
$var parameter 3 ) COMPLETED $end
$var parameter 3 * IDLE $end
$var parameter 4 + M_MAX $end
$var parameter 4 , N_MAX $end
$var parameter 3 - RUN_H $end
$var parameter 3 . RUN_L $end
$var reg 1 # bist_end $end
$var reg 1 / m_en $end
$var reg 1 0 m_rst $end
$var reg 1 1 n_en $end
$var reg 1 2 n_rst $end
$var reg 3 3 n_state [2:0] $end
$var reg 1 " out $end
$var reg 1 4 p_start $end
$var reg 1 5 pos_start $end
$var reg 1 ! running $end
$var reg 3 6 state [2:0] $end
$scope module m_counter $end
$var wire 1 $ clk $end
$var wire 1 / enable $end
$var wire 1 0 reset $end
$var reg 4 7 count [3:0] $end
$upscope $end
$scope module n_counter $end
$var wire 1 $ clk $end
$var wire 1 1 enable $end
$var wire 1 2 reset $end
$var reg 4 8 count [3:0] $end
$upscope $end
$upscope $end
$upscope $end
$enddefinitions $end
$comment Show the parameter values. $end
$dumpall
b10 .
b1 -
b1000 ,
b1001 +
b0 *
b11 )
$end
#0
$dumpvars
bx 8
bx 7
bx 6
x5
x4
bx 3
x2
x1
x0
x/
bx (
bx '
0&
0%
0$
x#
x"
x!
$end
#10000
b0 3
12
01
10
0/
0!
0#
0"
04
05
1$
#20000
0$
#30000
b0 6
b0 (
b0 7
b0 '
b0 8
1$
#40000
0$
#50000
1$
#60000
0$
#70000
1$
#80000
0$
#90000
1$
#100000
0$
#110000
1$
#120000
0$
#130000
1$
#140000
0$
#150000
1$
#160000
0$
#170000
1$
#180000
0$
#190000
1$
#200000
0$
1%
#210000
1$
#220000
0$
#230000
1$
#240000
0$
#250000
1$
#260000
0$
#270000
1$
#280000
0$
#290000
1$
#300000
0$
#310000
1$
#320000
0$
#330000
1$
#340000
0$
#350000
1$
#360000
0$
#370000
1$
#380000
0$
#390000
1$
#400000
0$
0%
#410000
1$
#420000
0$
#430000
1$
#440000
0$
#450000
1$
#460000
0$
#470000
1$
#480000
0$
#490000
1$
#500000
0$
1&
#510000
b1 3
14
15
1$
#520000
0$
#530000
00
02
11
1!
1"
b1 6
05
1$
#540000
0$
#550000
04
b1 '
b1 8
1$
0&
#560000
0$
#570000
b10 '
b10 8
1$
#580000
0$
#590000
b11 '
b11 8
1$
#600000
0$
#610000
b100 '
b100 8
1$
#620000
0$
#630000
b101 '
b101 8
1$
#640000
0$
#650000
b110 '
b110 8
1$
#660000
0$
#670000
b10 3
b111 '
b111 8
1$
#680000
0$
#690000
b1 3
1/
12
01
0"
b1000 '
b1000 8
b10 6
1$
#700000
0$
#710000
0/
02
11
1"
b1 6
b1 (
b1 7
b0 '
b0 8
1$
#720000
0$
#730000
b1 '
b1 8
1$
#740000
0$
#750000
b10 '
b10 8
1$
#760000
0$
#770000
b11 '
b11 8
1$
#780000
0$
#790000
b100 '
b100 8
1$
#800000
0$
#810000
b101 '
b101 8
1$
#820000
0$
#830000
b110 '
b110 8
1$
#840000
0$
#850000
b10 3
b111 '
b111 8
1$
#860000
0$
#870000
b1 3
1/
12
01
0"
b10 6
b1000 '
b1000 8
1$
#880000
0$
#890000
0/
02
11
1"
b0 '
b0 8
b10 (
b10 7
b1 6
1$
#900000
0$
#910000
b1 '
b1 8
1$
#920000
0$
#930000
b10 '
b10 8
1$
#940000
0$
#950000
b11 '
b11 8
1$
#960000
0$
#970000
b100 '
b100 8
1$
#980000
0$
#990000
b101 '
b101 8
1$
#1000000
0$
#1010000
b110 '
b110 8
1$
#1020000
0$
#1030000
b10 3
b111 '
b111 8
1$
#1040000
0$
#1050000
b1 3
1/
12
01
0"
b1000 '
b1000 8
b10 6
1$
#1060000
0$
#1070000
0/
02
11
1"
b1 6
b11 (
b11 7
b0 '
b0 8
1$
#1080000
0$
#1090000
b1 '
b1 8
1$
#1100000
0$
#1110000
b10 '
b10 8
1$
#1120000
0$
#1130000
b11 '
b11 8
1$
#1140000
0$
#1150000
b100 '
b100 8
1$
#1160000
0$
#1170000
b101 '
b101 8
1$
#1180000
0$
#1190000
b110 '
b110 8
1$
#1200000
0$
#1210000
b10 3
b111 '
b111 8
1$
#1220000
0$
#1230000
b1 3
1/
12
01
0"
b10 6
b1000 '
b1000 8
1$
#1240000
0$
#1250000
0/
02
11
1"
b0 '
b0 8
b100 (
b100 7
b1 6
1$
#1260000
0$
#1270000
b1 '
b1 8
1$
#1280000
0$
#1290000
b10 '
b10 8
1$
#1300000
0$
#1310000
b11 '
b11 8
1$
#1320000
0$
#1330000
b100 '
b100 8
1$
#1340000
0$
#1350000
b101 '
b101 8
1$
#1360000
0$
#1370000
b110 '
b110 8
1$
#1380000
0$
#1390000
b10 3
b111 '
b111 8
1$
#1400000
0$
#1410000
b1 3
1/
12
01
0"
b1000 '
b1000 8
b10 6
1$
#1420000
0$
#1430000
0/
02
11
1"
b1 6
b101 (
b101 7
b0 '
b0 8
1$
#1440000
0$
#1450000
b1 '
b1 8
1$
#1460000
0$
#1470000
b10 '
b10 8
1$
#1480000
0$
#1490000
b11 '
b11 8
1$
#1500000
0$
#1510000
b100 '
b100 8
1$
#1520000
0$
#1530000
b101 '
b101 8
1$
#1540000
0$
#1550000
b110 '
b110 8
1$
#1560000
0$
#1570000
b10 3
b111 '
b111 8
1$
#1580000
0$
#1590000
b1 3
1/
12
01
0"
b10 6
b1000 '
b1000 8
1$
#1600000
0$
#1610000
0/
02
11
1"
b0 '
b0 8
b110 (
b110 7
b1 6
1$
#1620000
0$
#1630000
b1 '
b1 8
1$
#1640000
0$
#1650000
b10 '
b10 8
1$
#1660000
0$
#1670000
b11 '
b11 8
1$
#1680000
0$
#1690000
b100 '
b100 8
1$
#1700000
0$
#1710000
b101 '
b101 8
1$
#1720000
0$
#1730000
b110 '
b110 8
1$
#1740000
0$
#1750000
b10 3
b111 '
b111 8
1$
#1760000
0$
#1770000
b1 3
1/
12
01
0"
b1000 '
b1000 8
b10 6
1$
#1780000
0$
#1790000
0/
02
11
1"
b1 6
b111 (
b111 7
b0 '
b0 8
1$
#1800000
0$
#1810000
b1 '
b1 8
1$
#1820000
0$
#1830000
b10 '
b10 8
1$
#1840000
0$
#1850000
b11 '
b11 8
1$
#1860000
0$
#1870000
b100 '
b100 8
1$
#1880000
0$
#1890000
b101 '
b101 8
1$
#1900000
0$
#1910000
b110 '
b110 8
1$
#1920000
0$
#1930000
b10 3
b111 '
b111 8
1$
#1940000
0$
#1950000
b1 3
1/
12
01
0"
b10 6
b1000 '
b1000 8
1$
#1960000
0$
#1970000
0/
02
11
1"
b0 '
b0 8
b1000 (
b1000 7
b1 6
1$
#1980000
0$
#1990000
b1 '
b1 8
1$
#2000000
0$
#2010000
b10 '
b10 8
1$
#2020000
0$
#2030000
b11 '
b11 8
1$
#2040000
0$
#2050000
b100 '
b100 8
1$
#2060000
0$
#2070000
b101 '
b101 8
1$
#2080000
0$
#2090000
b110 '
b110 8
1$
#2100000
0$
#2110000
b10 3
b111 '
b111 8
1$
#2120000
0$
#2130000
b1 3
1/
12
01
0"
b1000 '
b1000 8
b10 6
1$
#2140000
0$
#2150000
0/
02
11
1"
b1 6
b1001 (
b1001 7
b0 '
b0 8
1$
#2160000
0$
#2170000
b1 '
b1 8
1$
#2180000
0$
#2190000
b10 '
b10 8
1$
#2200000
0$
#2210000
b11 '
b11 8
1$
#2220000
0$
#2230000
b100 '
b100 8
1$
#2240000
0$
#2250000
b101 '
b101 8
1$
#2260000
0$
#2270000
b110 '
b110 8
1$
#2280000
0$
#2290000
b11 3
b111 '
b111 8
1$
#2300000
0$
#2310000
01
12
10
1#
0!
0"
b11 6
b1000 '
b1000 8
1$
#2320000
0$
#2330000
b0 '
b0 8
b0 (
b0 7
1$
#2340000
0$
#2350000
1$
#2360000
0$
#2370000
1$
#2380000
0$
#2390000
1$
#2400000
0$
#2410000
1$
#2420000
0$
#2430000
1$
#2440000
0$
#2450000
1$
#2460000
0$
#2470000
1$
#2480000
0$
#2490000
1$
#2500000
0$
#2510000
1$
#2520000
0$
#2530000
1$
#2540000
0$
#2550000
1$
#2560000
0$
#2570000
1$
#2580000
0$
#2590000
1$
#2600000
0$
#2610000
1$
#2620000
0$
#2630000
1$
#2640000
0$
#2650000
b1 3
14
15
1$
1&
#2660000
0$
#2670000
00
02
11
0#
1!
1"
05
b1 6
1$
#2680000
0$
#2690000
b1 '
b1 8
1$
#2700000
0$
0&
#2710000
04
b10 '
b10 8
1$
#2720000
0$
#2730000
b11 '
b11 8
1$
#2740000
0$
#2750000
b100 '
b100 8
1$
#2760000
0$
#2770000
b101 '
b101 8
1$
#2780000
0$
#2790000
b110 '
b110 8
1$
#2800000
0$
#2810000
b10 3
b111 '
b111 8
1$
#2820000
0$
#2830000
b1 3
1/
12
01
0"
b10 6
b1000 '
b1000 8
1$
#2840000
0$
#2850000
0/
02
11
1"
b0 '
b0 8
b1 (
b1 7
b1 6
1$
#2860000
0$
#2870000
b1 '
b1 8
1$
#2880000
0$
#2890000
b10 '
b10 8
1$
#2900000
0$
#2910000
b11 '
b11 8
1$
#2920000
0$
#2930000
b100 '
b100 8
1$
#2940000
0$
#2950000
b101 '
b101 8
1$
#2960000
0$
#2970000
b110 '
b110 8
1$
#2980000
0$
#2990000
b10 3
b111 '
b111 8
1$
#3000000
0$
#3010000
b1 3
1/
12
01
0"
b1000 '
b1000 8
b10 6
1$
#3020000
0$
#3030000
0/
02
11
1"
b1 6
b10 (
b10 7
b0 '
b0 8
1$
#3040000
0$
#3050000
b1 '
b1 8
1$
#3060000
0$
#3070000
b10 '
b10 8
1$
#3080000
0$
#3090000
b11 '
b11 8
1$
#3100000
0$
#3110000
b100 '
b100 8
1$
#3120000
0$
#3130000
b101 '
b101 8
1$
#3140000
0$
#3150000
b110 '
b110 8
1$
#3160000
0$
#3170000
b10 3
b111 '
b111 8
1$
#3180000
0$
#3190000
b1 3
1/
12
01
0"
b10 6
b1000 '
b1000 8
1$
#3200000
0$
#3210000
0/
02
11
1"
b0 '
b0 8
b11 (
b11 7
b1 6
1$
#3220000
0$
#3230000
b1 '
b1 8
1$
#3240000
0$
#3250000
b10 '
b10 8
1$
#3260000
0$
#3270000
b11 '
b11 8
1$
#3280000
0$
#3290000
b100 '
b100 8
1$
#3300000
0$
#3310000
b101 '
b101 8
1$
#3320000
0$
#3330000
b110 '
b110 8
1$
#3340000
0$
#3350000
b10 3
b111 '
b111 8
1$
#3360000
0$
#3370000
b1 3
1/
12
01
0"
b1000 '
b1000 8
b10 6
1$
#3380000
0$
#3390000
0/
02
11
1"
b1 6
b100 (
b100 7
b0 '
b0 8
1$
#3400000
0$
#3410000
b1 '
b1 8
1$
#3420000
0$
#3430000
b10 '
b10 8
1$
#3440000
0$
#3450000
b11 '
b11 8
1$
#3460000
0$
#3470000
b100 '
b100 8
1$
#3480000
0$
#3490000
b101 '
b101 8
1$
#3500000
0$
#3510000
b110 '
b110 8
1$
#3520000
0$
#3530000
b10 3
b111 '
b111 8
1$
#3540000
0$
#3550000
b1 3
1/
12
01
0"
b10 6
b1000 '
b1000 8
1$
#3560000
0$
#3570000
0/
02
11
1"
b0 '
b0 8
b101 (
b101 7
b1 6
1$
#3580000
0$
#3590000
b1 '
b1 8
1$
#3600000
0$
#3610000
b10 '
b10 8
1$
#3620000
0$
#3630000
b11 '
b11 8
1$
#3640000
0$
#3650000
b100 '
b100 8
1$
#3660000
0$
#3670000
b101 '
b101 8
1$
#3680000
0$
#3690000
b110 '
b110 8
1$
#3700000
0$
#3710000
b10 3
b111 '
b111 8
1$
#3720000
0$
#3730000
b1 3
1/
12
01
0"
b1000 '
b1000 8
b10 6
1$
#3740000
0$
#3750000
0/
02
11
1"
b1 6
b110 (
b110 7
b0 '
b0 8
1$
#3760000
0$
#3770000
b1 '
b1 8
1$
#3780000
0$
#3790000
b10 '
b10 8
1$
#3800000
0$
#3810000
b11 '
b11 8
1$
#3820000
0$
#3830000
b100 '
b100 8
1$
#3840000
0$
#3850000
b101 '
b101 8
1$
#3860000
0$
#3870000
b110 '
b110 8
1$
#3880000
0$
#3890000
b10 3
b111 '
b111 8
1$
#3900000
0$
#3910000
b1 3
1/
12
01
0"
b10 6
b1000 '
b1000 8
1$
#3920000
0$
#3930000
0/
02
11
1"
b0 '
b0 8
b111 (
b111 7
b1 6
1$
#3940000
0$
#3950000
b1 '
b1 8
1$
#3960000
0$
#3970000
b10 '
b10 8
1$
#3980000
0$
#3990000
b11 '
b11 8
1$
#4000000
0$
#4010000
b100 '
b100 8
1$
#4020000
0$
#4030000
b101 '
b101 8
1$
#4040000
0$
#4050000
b110 '
b110 8
1$
#4060000
0$
#4070000
b10 3
b111 '
b111 8
1$
#4080000
0$
#4090000
b1 3
1/
12
01
0"
b1000 '
b1000 8
b10 6
1$
#4100000
0$
#4110000
0/
02
11
1"
b1 6
b1000 (
b1000 7
b0 '
b0 8
1$
#4120000
0$
#4130000
b1 '
b1 8
1$
#4140000
0$
#4150000
b10 '
b10 8
1$
#4160000
0$
#4170000
b11 '
b11 8
1$
#4180000
0$
#4190000
b100 '
b100 8
1$
#4200000
0$
#4210000
b101 '
b101 8
1$
#4220000
0$
#4230000
b110 '
b110 8
1$
#4240000
0$
#4250000
b10 3
b111 '
b111 8
1$
#4260000
0$
#4270000
b1 3
1/
12
01
0"
b10 6
b1000 '
b1000 8
1$
#4280000
0$
#4290000
0/
02
11
1"
b0 '
b0 8
b1001 (
b1001 7
b1 6
1$
#4300000
0$
#4310000
b1 '
b1 8
1$
#4320000
0$
#4330000
b10 '
b10 8
1$
#4340000
0$
#4350000
b11 '
b11 8
1$
#4360000
0$
#4370000
b100 '
b100 8
1$
#4380000
0$
#4390000
b101 '
b101 8
1$
#4400000
0$
#4410000
b110 '
b110 8
1$
#4420000
0$
#4430000
b11 3
b111 '
b111 8
1$
#4440000
0$
#4450000
01
12
10
1#
0!
0"
b1000 '
b1000 8
b11 6
1$
#4460000
0$
#4470000
b0 (
b0 7
b0 '
b0 8
1$
#4480000
0$
#4490000
1$
#4500000
0$
#4510000
1$
#4520000
0$
#4530000
1$
#4540000
0$
#4550000
1$
#4560000
0$
#4570000
1$
#4580000
0$
#4590000
1$
#4600000
0$
#4610000
1$
#4620000
0$
#4630000
1$
#4640000
0$
#4650000
1$
#4660000
0$
#4670000
1$
#4680000
0$
#4690000
1$
#4700000
0$
1%
#4710000
b0 3
0#
b0 6
1$
#4720000
0$
#4730000
1$
#4740000
0$
#4750000
b1 3
14
15
1$
1&
#4760000
0$
#4770000
b0 3
05
1$
#4780000
0$
#4790000
1$
#4800000
0$
0&
#4810000
04
1$
