proj1/params.v
`define N_MAX 8
`define M_MAX 9

proj1/counter_control.v
`timescale 100ps / 1ps 
`include "params.v" 

module counter_control(
    input clk,
    input reset,
    input enable,
    input [3:0] n,
    input [3:0] m,
    output reg n_reset,
    output reg m_reset,
    output reg n_enable,
    output reg m_enable,
    output reg out,
    output reg done);
    
    always @(*) begin
        if (reset == 1) begin
            out = 0;
            done = 0;
            n_reset = 1;
            m_reset = 1;
            n_enable = 0;
            m_enable = 0;
        end
        else if (enable == 1) begin
            if (n == `N_MAX && m == `M_MAX) begin
                out = 0;
                done = 1;
                n_reset = 1;
                m_reset = 1;
                n_enable = 0;
                m_enable = 0;
            end
            else if (n == `N_MAX) begin
                out = 0;
                m_enable = 1;
            end
            else if (n == `N_MAX+1) begin
                done = 0;
                out = 0;
                n_enable = 0;
                n_reset = 1;
                m_enable = 1; 
                m_reset = 0;
            end
            else begin
                done = 0;
                out = 1;
                n_enable = 1;
                n_reset = 0;
                m_enable = 0;
                m_reset = 0;
            end
        end
        else begin
            out = 0;
            done = 0;
            n_enable = 0;
            m_enable = 0;
        end
    end

endmodule

proj1/counter_4b.v
`timescale 100ps / 1ps 

module counter_4b(input clk, input reset, input enable, output reg [3:0] count);
    
    always @(posedge clk or posedge reset) begin
        if (reset == 1)
            count <= 4'd0;
        else if (enable == 1)
            count <= count + 4'd1;
    end

endmodule

proj1/controller.v
`timescale 100ps / 1ps 

////////////////////////////////////////////////////////////////////////////////// 
//
// Company: Instituto Superior Técnico de Lisboa 
// Module Name: pulseproj
// Description: pulse generator
// 
////////////////////////////////////////////////////////////////////////////////// 
// 0.1 us clock

module controller(
    input clk,
    input start,
    input reset,
    output reg out,
    output reg bist_end,
    output reg running);

    // State Flip-flops
    reg [2:0] state, n_state;
    
    // State coding
    localparam [2:0] IDLE = 0, RUN = 1, COMPLETED = 2;

    // M and N 
    localparam [3:0] N_MAX = 8;
    localparam [3:0] M_MAX = 9;

    // Regs
    reg pos_start;
    wire [3:0] n, m;

    // wires
    wire n_en, n_rst;
    wire m_en, m_rst;
    reg cnt_ctrl_en, cnt_ctrl_rst; 
    wire cnt_ctrl_out, cnt_ctrl_done;




    always @(posedge clk) begin

        if (reset == 1)
            state = IDLE;
        else
            state = n_state;

    end

    always @(*) begin
    
        case (state)
        IDLE: begin
            // Outputs
            out = 0;
            bist_end = 0;
            running = 0;
            // module regs
            /*n = 0;
            m = 0;*/
            // Counter control
            cnt_ctrl_rst = 1;
            cnt_ctrl_en = 0;

            // Defining the next state
            if (pos_start == 1) begin
                n_state = RUN;
                pos_start = 0;
                /*
                n_en = 1;
                n_rst = 0;*/
            end
            else
                n_state = state;
        end

        RUN: begin

            if (cnt_ctrl_done == 0) begin
                cnt_ctrl_rst = 0;
                cnt_ctrl_en = 1;
            end
            else begin
                cnt_ctrl_en = 0;
                cnt_ctrl_rst = 1;
            end

            /*if (n == N_MAX-1 && m == M_MAX)
                n_state = COMPLETED;
            else if (n == N_MAX) begin
                out = 0;

                n_rst = 1;

                m_en = 1;
                m_rst = 0;

                n_state = state;
            end
            else begin
                out = 1;

                n_rst = 0;
                n_en = 1;

                m_en = 0;
                m_rst = 1;

                n_state = state;
            end */
        end
        
        COMPLETED: begin

        end

        default: n_state = IDLE;
        endcase
    end

    // Detects L to H transition on START input
    always @(posedge start) begin
        pos_start = 1;
    end

    // Counters
    counter_4b n_counter (
        .clk(clk),
        .reset(n_rst),
        .enable(n_en),
        .count(n)
    );
    counter_4b m_counter (
        .clk(clk),
        .reset(m_rst),
        .enable(m_en),
        .count(m)
    );

    // Counter control
    counter_control counter_control(
        .clk(clk),
        .reset(cnt_ctrl_rst),
        .enable(cnt_ctrl_en),
        .n(n),
        .m(m),
        .n_reset(n_rst),
        .m_reset(m_rst),
        .n_enable(n_en),
        .m_enable(m_en),
        .out(cnt_ctrl_out),
        .done(cnt_ctrl_done)
    );

endmodule

proj1/controller_tb.v
`timescale 1ns / 1ps
//`timescale 10ns / 1ns delete this one
////////////////////////////////////////////////////////////////////////////////

module controller_tb;

	reg clk, start, reset;
	wire out, bist_end, running;
	
	controller controller (
			.clk(clk),
			.start(start),
			.reset(reset),
			.out(out),
			.bist_end(bist_end),
			.running(running)
			);

	initial 
		begin
		 $dumpfile("controller_tb.vcd");
		 $dumpvars(0,controller_tb);

		 clk=0;
		 start=0;
		 reset=0;
		end
   
	always
//		#50 clk = !clk; 
		#10 clk = !clk; 

	initial
	  	begin
		 #200 reset=1; // Test reset
		 #200 reset=0;
		 #100 start=1; // test start
		 #50  start=0;
		 #2000 $finish;	
		end 
   			
endmodule

proj1/controller_tb.vcd
$date
	Sun Nov 19 19:11:43 2023
$end
$version
	Icarus Verilog
$end
$timescale
	1ps
$end
$scope module controller_tb $end
$var wire 1 ! running $end
$var wire 1 " out $end
$var wire 1 # bist_end $end
$var reg 1 $ clk $end
$var reg 1 % reset $end
$var reg 1 & start $end
$scope module controller $end
$var wire 1 $ clk $end
$var wire 1 % reset $end
$var wire 1 & start $end
$var wire 1 ' n_rst $end
$var wire 1 ( n_en $end
$var wire 4 ) n [3:0] $end
$var wire 1 * m_rst $end
$var wire 1 + m_en $end
$var wire 4 , m [3:0] $end
$var wire 1 - cnt_ctrl_out $end
$var wire 1 . cnt_ctrl_done $end
$var parameter 3 / COMPLETED $end
$var parameter 3 0 IDLE $end
$var parameter 4 1 M_MAX $end
$var parameter 4 2 N_MAX $end
$var parameter 3 3 RUN $end
$var reg 1 # bist_end $end
$var reg 1 4 cnt_ctrl_en $end
$var reg 1 5 cnt_ctrl_rst $end
$var reg 3 6 n_state [2:0] $end
$var reg 1 " out $end
$var reg 1 7 pos_start $end
$var reg 1 ! running $end
$var reg 3 8 state [2:0] $end
$scope module counter_control $end
$var wire 1 $ clk $end
$var wire 1 4 enable $end
$var wire 1 5 reset $end
$var wire 4 9 n [3:0] $end
$var wire 4 : m [3:0] $end
$var reg 1 . done $end
$var reg 1 + m_enable $end
$var reg 1 * m_reset $end
$var reg 1 ( n_enable $end
$var reg 1 ' n_reset $end
$var reg 1 - out $end
$upscope $end
$scope module m_counter $end
$var wire 1 $ clk $end
$var wire 1 + enable $end
$var wire 1 * reset $end
$var reg 4 ; count [3:0] $end
$upscope $end
$scope module n_counter $end
$var wire 1 $ clk $end
$var wire 1 ( enable $end
$var wire 1 ' reset $end
$var reg 4 < count [3:0] $end
$upscope $end
$upscope $end
$upscope $end
$enddefinitions $end
$comment Show the parameter values. $end
$dumpall
b1 3
b1000 2
b1001 1
b0 0
b10 /
$end
#0
$dumpvars
bx <
bx ;
bx :
bx 9
bx 8
x7
bx 6
x5
x4
x.
x-
bx ,
x+
x*
bx )
x(
x'
0&
0%
0$
x#
x"
x!
$end
#10000
1$
#20000
0$
#30000
1$
#40000
0$
#50000
1$
#60000
0$
#70000
1$
#80000
0$
#90000
1$
#100000
0$
#110000
1$
#120000
0$
#130000
1$
#140000
0$
#150000
1$
#160000
0$
#170000
1$
#180000
0$
#190000
1$
#200000
0$
1%
#210000
b0 ,
b0 :
b0 ;
b0 )
b0 9
b0 <
0+
0(
1*
1'
0.
0-
b0 6
04
15
0!
0#
0"
b0 8
1$
#220000
0$
#230000
1$
#240000
0$
#250000
1$
#260000
0$
#270000
1$
#280000
0$
#290000
1$
#300000
0$
#310000
1$
#320000
0$
#330000
1$
#340000
0$
#350000
1$
#360000
0$
#370000
1$
#380000
0$
#390000
1$
#400000
0$
0%
#410000
1$
#420000
0$
#430000
1$
#440000
0$
#450000
1$
#460000
0$
#470000
1$
#480000
0$
#490000
1$
#500000
b1 6
07
0$
1&
#510000
0*
0'
1(
1-
14
05
b1 8
1$
#520000
0$
#530000
b1 )
b1 9
b1 <
1$
#540000
0$
#550000
b10 )
b10 9
b10 <
1$
0&
#560000
0$
#570000
b11 )
b11 9
b11 <
1$
#580000
0$
#590000
b100 )
b100 9
b100 <
1$
#600000
0$
#610000
b101 )
b101 9
b101 <
1$
#620000
0$
#630000
b110 )
b110 9
b110 <
1$
#640000
0$
#650000
b111 )
b111 9
b111 <
1$
#660000
0$
#670000
1+
0-
b1000 )
b1000 9
b1000 <
1$
#680000
0$
#690000
0+
1-
0'
1(
b1 ,
b1 :
b1 ;
b0 )
b0 9
b0 <
1$
#700000
0$
#710000
b1 )
b1 9
b1 <
1$
#720000
0$
#730000
b10 )
b10 9
b10 <
1$
#740000
0$
#750000
b11 )
b11 9
b11 <
1$
#760000
0$
#770000
b100 )
b100 9
b100 <
1$
#780000
0$
#790000
b101 )
b101 9
b101 <
1$
#800000
0$
#810000
b110 )
b110 9
b110 <
1$
#820000
0$
#830000
b111 )
b111 9
b111 <
1$
#840000
0$
#850000
1+
0-
b1000 )
b1000 9
b1000 <
1$
#860000
0$
#870000
0+
1-
0'
1(
b10 ,
b10 :
b10 ;
b0 )
b0 9
b0 <
1$
#880000
0$
#890000
b1 )
b1 9
b1 <
1$
#900000
0$
#910000
b10 )
b10 9
b10 <
1$
#920000
0$
#930000
b11 )
b11 9
b11 <
1$
#940000
0$
#950000
b100 )
b100 9
b100 <
1$
#960000
0$
#970000
b101 )
b101 9
b101 <
1$
#980000
0$
#990000
b110 )
b110 9
b110 <
1$
#1000000
0$
#1010000
b111 )
b111 9
b111 <
1$
#1020000
0$
#1030000
1+
0-
b1000 )
b1000 9
b1000 <
1$
#1040000
0$
#1050000
0+
1-
0'
1(
b11 ,
b11 :
b11 ;
b0 )
b0 9
b0 <
1$
#1060000
0$
#1070000
b1 )
b1 9
b1 <
1$
#1080000
0$
#1090000
b10 )
b10 9
b10 <
1$
#1100000
0$
#1110000
b11 )
b11 9
b11 <
1$
#1120000
0$
#1130000
b100 )
b100 9
b100 <
1$
#1140000
0$
#1150000
b101 )
b101 9
b101 <
1$
#1160000
0$
#1170000
b110 )
b110 9
b110 <
1$
#1180000
0$
#1190000
b111 )
b111 9
b111 <
1$
#1200000
0$
#1210000
1+
0-
b1000 )
b1000 9
b1000 <
1$
#1220000
0$
#1230000
0+
1-
0'
1(
b100 ,
b100 :
b100 ;
b0 )
b0 9
b0 <
1$
#1240000
0$
#1250000
b1 )
b1 9
b1 <
1$
#1260000
0$
#1270000
b10 )
b10 9
b10 <
1$
#1280000
0$
#1290000
b11 )
b11 9
b11 <
1$
#1300000
0$
#1310000
b100 )
b100 9
b100 <
1$
#1320000
0$
#1330000
b101 )
b101 9
b101 <
1$
#1340000
0$
#1350000
b110 )
b110 9
b110 <
1$
#1360000
0$
#1370000
b111 )
b111 9
b111 <
1$
#1380000
0$
#1390000
1+
0-
b1000 )
b1000 9
b1000 <
1$
#1400000
0$
#1410000
0+
1-
0'
1(
b101 ,
b101 :
b101 ;
b0 )
b0 9
b0 <
1$
#1420000
0$
#1430000
b1 )
b1 9
b1 <
1$
#1440000
0$
#1450000
b10 )
b10 9
b10 <
1$
#1460000
0$
#1470000
b11 )
b11 9
b11 <
1$
#1480000
0$
#1490000
b100 )
b100 9
b100 <
1$
#1500000
0$
#1510000
b101 )
b101 9
b101 <
1$
#1520000
0$
#1530000
b110 )
b110 9
b110 <
1$
#1540000
0$
#1550000
b111 )
b111 9
b111 <
1$
#1560000
0$
#1570000
1+
0-
b1000 )
b1000 9
b1000 <
1$
#1580000
0$
#1590000
0+
1-
0'
1(
b110 ,
b110 :
b110 ;
b0 )
b0 9
b0 <
1$
#1600000
0$
#1610000
b1 )
b1 9
b1 <
1$
#1620000
0$
#1630000
b10 )
b10 9
b10 <
1$
#1640000
0$
#1650000
b11 )
b11 9
b11 <
1$
#1660000
0$
#1670000
b100 )
b100 9
b100 <
1$
#1680000
0$
#1690000
b101 )
b101 9
b101 <
1$
#1700000
0$
#1710000
b110 )
b110 9
b110 <
1$
#1720000
0$
#1730000
b111 )
b111 9
b111 <
1$
#1740000
0$
#1750000
1+
0-
b1000 )
b1000 9
b1000 <
1$
#1760000
0$
#1770000
0+
1-
0'
1(
b111 ,
b111 :
b111 ;
b0 )
b0 9
b0 <
1$
#1780000
0$
#1790000
b1 )
b1 9
b1 <
1$
#1800000
0$
#1810000
b10 )
b10 9
b10 <
1$
#1820000
0$
#1830000
b11 )
b11 9
b11 <
1$
#1840000
0$
#1850000
b100 )
b100 9
b100 <
1$
#1860000
0$
#1870000
b101 )
b101 9
b101 <
1$
#1880000
0$
#1890000
b110 )
b110 9
b110 <
1$
#1900000
0$
#1910000
b111 )
b111 9
b111 <
1$
#1920000
0$
#1930000
1+
0-
b1000 )
b1000 9
b1000 <
1$
#1940000
0$
#1950000
0+
1-
0'
1(
b1000 ,
b1000 :
b1000 ;
b0 )
b0 9
b0 <
1$
#1960000
0$
#1970000
b1 )
b1 9
b1 <
1$
#1980000
0$
#1990000
b10 )
b10 9
b10 <
1$
#2000000
0$
#2010000
b11 )
b11 9
b11 <
1$
#2020000
0$
#2030000
b100 )
b100 9
b100 <
1$
#2040000
0$
#2050000
b101 )
b101 9
b101 <
1$
#2060000
0$
#2070000
b110 )
b110 9
b110 <
1$
#2080000
0$
#2090000
b111 )
b111 9
b111 <
1$
#2100000
0$
#2110000
1+
0-
b1000 )
b1000 9
b1000 <
1$
#2120000
0$
#2130000
0+
1-
0'
1(
b1001 ,
b1001 :
b1001 ;
b0 )
b0 9
b0 <
1$
#2140000
0$
#2150000
b1 )
b1 9
b1 <
1$
#2160000
0$
#2170000
b10 )
b10 9
b10 <
1$
#2180000
0$
#2190000
b11 )
b11 9
b11 <
1$
#2200000
0$
#2210000
b100 )
b100 9
b100 <
1$
#2220000
0$
#2230000
b101 )
b101 9
b101 <
1$
#2240000
0$
#2250000
b110 )
b110 9
b110 <
1$
#2260000
0$
#2270000
b111 )
b111 9
b111 <
1$
